search_similar_image/__init__.py
search_similar_image/model/__init__.py
search_similar_image/model/search_model.py
search_similar_image/utils/data_utils.py
search_similar_image/utils/model_utils.py
search_similar_image-0.1.0.dist-info/METADATA
search_similar_image-0.1.0.dist-info/WHEEL
search_similar_image-0.1.0.dist-info/RECORD
