Metadata-Version: 2.1
Name: search-similar-image
Version: 0.1.0
Summary: 
Home-page: https://github.com/tocom242242
Author: tocom
Author-email: tcom242242@gmail.com
Requires-Python: >=3.10,<4.0
Classifier: Programming Language :: Python :: 3
Classifier: Programming Language :: Python :: 3.10
Classifier: Programming Language :: Python :: 3.11
Requires-Dist: faiss-cpu (>=1.7.3,<2.0.0)
Requires-Dist: pdoc3 (>=0.10.0,<0.11.0)
Requires-Dist: timm (>=0.6.12,<0.7.0)
Project-URL: Repository, https://github.com/tocom242242/search_similar_image
